tarea7/checker.v
module checker#(parameter BUS_SIZE = 16,
				parameter WORD_SIZE = 4,
				parameter WORD_NUM = BUS_SIZE / WORD_SIZE
				)(input error,
				input error_sint,
				input [BUS_SIZE-1:0] data_out_bus,
				input [BUS_SIZE-1:0] data_out_bus_sint,
				input [WORD_NUM-1:0] control_out,
				input [WORD_SIZE-1:0] control_out_sint,
				output reg check_out,
				output reg check_control,
				output reg check_error
				);
				
	always @(*) begin
		if(data_out_bus != data_out_bus_sint) begin
			check_out = 1;
		end else check_out = 0;

		if(control_out != control_out_sint) begin
			check_control = 1;
		end else check_control = 0;
	
		if(error_sint != error) begin
			check_error = 1;
		end else check_error = 0;
	end

endmodule

tarea5/cmos_cells_retardos.v

module BUF(A, Y);
input A;
output Y;
assign #(1.4:4.1:4.1) Y = A;
endmodule

module NOT(A, Y);
input A;
output Y;
assign #(1:3.5:6, 1:3.5:6) Y = ~A;
endmodule

module NAND(A, B, Y); //SN74LVC1G38
input A, B;
output Y;
assign #(0.9:1.6:2.4, 0.9:1.6:2.4) Y = ~(A & B);
endmodule

module NOR(A, B, Y);
input A, B;
output Y;
assign #(0.8:2.1:3.4, 0.8:2.1:3.4) Y = ~(A | B);
endmodule

module DFF(C, D, Q); //(1.1:2.4:3.8)
input C, D;
output reg Q;
always @(posedge C)
	#(1.1:2.4:3.8) Q <= D;
endmodule

module DFFSR(C, D, Q, S, R);
//assign #(1:3.5:6, 1:3.5:6)
input C, D, S, R;
output reg Q;
always @(posedge C, posedge S, posedge R)
	if (S)
		Q <= 1'b1;
	else if (R)
		Q <= 1'b0;
	else
		Q <= D;
endmodule

tarea7/state_machine_sintetizado.v
/* Generated by Yosys 0.9 (git sha1 1979e0b) */

(* dynports =  1  *)
(* cells_not_processed =  1  *)
(* src = "state_machine_sintetizado.v:1" *)
module state_machine_sintetizado(reset, clk, data_bus, data_out_bus_sint, control_out_sint, error_sint);
  (* src = "state_machine_sintetizado.v:27" *)
  wire [4:0] _000_;
  (* src = "state_machine_sintetizado.v:27" *)
  wire _001_;
  (* src = "state_machine_sintetizado.v:27" *)
  wire [3:0] _002_;
  (* src = "state_machine_sintetizado.v:47" *)
  wire _003_;
  (* src = "state_machine_sintetizado.v:27" *)
  wire [4:0] _004_;
  wire _005_;
  wire _006_;
  wire _007_;
  wire _008_;
  wire _009_;
  wire _010_;
  (* src = "state_machine_sintetizado.v:14" *)
  wire _011_;
  (* src = "state_machine_sintetizado.v:14" *)
  wire _012_;
  wire _013_;
  wire _014_;
  wire _015_;
  wire _016_;
  wire _017_;
  wire _018_;
  wire _019_;
  wire _020_;
  wire _021_;
  wire _022_;
  wire _023_;
  wire _024_;
  wire _025_;
  wire _026_;
  wire _027_;
  wire _028_;
  wire _029_;
  wire _030_;
  wire _031_;
  wire _032_;
  wire _033_;
  wire _034_;
  wire _035_;
  wire _036_;
  wire _037_;
  wire _038_;
  wire _039_;
  wire _040_;
  wire _041_;
  wire _042_;
  wire _043_;
  wire _044_;
  wire _045_;
  wire _046_;
  wire _047_;
  wire _048_;
  wire _049_;
  wire _050_;
  wire _051_;
  wire _052_;
  wire _053_;
  wire _054_;
  wire _055_;
  wire _056_;
  wire _057_;
  wire _058_;
  wire _059_;
  wire _060_;
  wire _061_;
  wire _062_;
  wire _063_;
  wire _064_;
  wire _065_;
  wire _066_;
  wire _067_;
  wire _068_;
  wire _069_;
  wire _070_;
  wire _071_;
  wire _072_;
  wire _073_;
  wire _074_;
  wire _075_;
  wire _076_;
  wire _077_;
  wire _078_;
  wire _079_;
  wire _080_;
  wire _081_;
  wire _082_;
  wire _083_;
  wire _084_;
  wire _085_;
  wire _086_;
  wire _087_;
  wire _088_;
  wire _089_;
  wire _090_;
  wire _091_;
  wire _092_;
  wire _093_;
  wire _094_;
  wire _095_;
  wire _096_;
  wire _097_;
  wire _098_;
  wire _099_;
  wire _100_;
  wire _101_;
  wire _102_;
  (* src = "state_machine_sintetizado.v:18" *)
  wire [3:0] buffer;
  (* src = "state_machine_sintetizado.v:6" *)
  input clk;
  (* src = "state_machine_sintetizado.v:9" *)
  output [3:0] control_out_sint;
  (* src = "state_machine_sintetizado.v:15" *)
  wire [4:0] counter;
  (* src = "state_machine_sintetizado.v:7" *)
  input [15:0] data_bus;
  (* src = "state_machine_sintetizado.v:8" *)
  output [15:0] data_out_bus_sint;
  (* src = "state_machine_sintetizado.v:10" *)
  output error_sint;
  (* src = "state_machine_sintetizado.v:18" *)
  wire [3:0] f_code;
  (* src = "state_machine_sintetizado.v:16" *)
  wire next_error_sint;
  (* src = "state_machine_sintetizado.v:14" *)
  (* unused_bits = "0 1 2" *)
  wire [4:0] next_state;
  (* src = "state_machine_sintetizado.v:5" *)
  input reset;
  (* onehot = 32'd1 *)
  wire [4:0] state;
  NOT _103_ (
    .A(state[1]),
    .Y(_048_)
  );
  NOT _104_ (
    .A(state[4]),
    .Y(_049_)
  );
  NOT _105_ (
    .A(state[0]),
    .Y(_050_)
  );
  NOT _106_ (
    .A(f_code[3]),
    .Y(_051_)
  );
  NOT _107_ (
    .A(reset),
    .Y(_005_)
  );
  NOT _108_ (
    .A(f_code[2]),
    .Y(_052_)
  );
  NOT _109_ (
    .A(next_error_sint),
    .Y(_053_)
  );
  NOT _110_ (
    .A(data_bus[1]),
    .Y(_054_)
  );
  NOT _111_ (
    .A(data_bus[2]),
    .Y(_055_)
  );
  NOT _112_ (
    .A(data_bus[14]),
    .Y(_056_)
  );
  NOT _113_ (
    .A(data_bus[15]),
    .Y(_057_)
  );
  NAND _114_ (
    .A(f_code[1]),
    .B(data_bus[13]),
    .Y(_058_)
  );
  NOT _115_ (
    .A(_058_),
    .Y(_059_)
  );
  NOR _116_ (
    .A(f_code[1]),
    .B(data_bus[13]),
    .Y(_060_)
  );
  NOT _117_ (
    .A(_060_),
    .Y(_061_)
  );
  NAND _118_ (
    .A(_058_),
    .B(_061_),
    .Y(_062_)
  );
  NOR _119_ (
    .A(_059_),
    .B(_060_),
    .Y(_063_)
  );
  NAND _120_ (
    .A(f_code[0]),
    .B(data_bus[12]),
    .Y(_064_)
  );
  NOT _121_ (
    .A(_064_),
    .Y(_065_)
  );
  NOR _122_ (
    .A(f_code[0]),
    .B(data_bus[12]),
    .Y(_066_)
  );
  NOT _123_ (
    .A(_066_),
    .Y(_067_)
  );
  NAND _124_ (
    .A(_064_),
    .B(_067_),
    .Y(_068_)
  );
  NOR _125_ (
    .A(_065_),
    .B(_066_),
    .Y(_069_)
  );
  NOR _126_ (
    .A(_063_),
    .B(_069_),
    .Y(_070_)
  );
  NAND _127_ (
    .A(_062_),
    .B(_068_),
    .Y(_071_)
  );
  NOR _128_ (
    .A(_051_),
    .B(data_bus[15]),
    .Y(_072_)
  );
  NAND _129_ (
    .A(f_code[3]),
    .B(_057_),
    .Y(_073_)
  );
  NOR _130_ (
    .A(f_code[3]),
    .B(_057_),
    .Y(_074_)
  );
  NAND _131_ (
    .A(_051_),
    .B(data_bus[15]),
    .Y(_075_)
  );
  NOR _132_ (
    .A(_072_),
    .B(_074_),
    .Y(_076_)
  );
  NAND _133_ (
    .A(_073_),
    .B(_075_),
    .Y(_077_)
  );
  NOR _134_ (
    .A(_052_),
    .B(data_bus[14]),
    .Y(_078_)
  );
  NAND _135_ (
    .A(f_code[2]),
    .B(_056_),
    .Y(_079_)
  );
  NOR _136_ (
    .A(f_code[2]),
    .B(_056_),
    .Y(_080_)
  );
  NAND _137_ (
    .A(_052_),
    .B(data_bus[14]),
    .Y(_081_)
  );
  NOR _138_ (
    .A(_078_),
    .B(_080_),
    .Y(_082_)
  );
  NAND _139_ (
    .A(_079_),
    .B(_081_),
    .Y(_083_)
  );
  NOR _140_ (
    .A(_077_),
    .B(_083_),
    .Y(_084_)
  );
  NAND _141_ (
    .A(_076_),
    .B(_082_),
    .Y(_085_)
  );
  NOR _142_ (
    .A(_071_),
    .B(_085_),
    .Y(_086_)
  );
  NAND _143_ (
    .A(_070_),
    .B(_084_),
    .Y(_087_)
  );
  NAND _144_ (
    .A(reset),
    .B(_086_),
    .Y(_088_)
  );
  NOT _145_ (
    .A(_088_),
    .Y(_089_)
  );
  NOR _146_ (
    .A(counter[4]),
    .B(data_bus[0]),
    .Y(_090_)
  );
  NAND _147_ (
    .A(_054_),
    .B(_055_),
    .Y(_091_)
  );
  NOR _148_ (
    .A(data_bus[3]),
    .B(_091_),
    .Y(_092_)
  );
  NAND _149_ (
    .A(_090_),
    .B(_092_),
    .Y(_093_)
  );
  NOT _150_ (
    .A(_093_),
    .Y(_094_)
  );
  NOR _151_ (
    .A(state[3]),
    .B(state[2]),
    .Y(_095_)
  );
  NOT _152_ (
    .A(_095_),
    .Y(_096_)
  );
  NOR _153_ (
    .A(_093_),
    .B(_095_),
    .Y(_097_)
  );
  NAND _154_ (
    .A(_089_),
    .B(_097_),
    .Y(_098_)
  );
  NOT _155_ (
    .A(_098_),
    .Y(_006_)
  );
  NAND _156_ (
    .A(reset),
    .B(_087_),
    .Y(_099_)
  );
  NAND _157_ (
    .A(_048_),
    .B(_049_),
    .Y(_100_)
  );
  NOR _158_ (
    .A(_096_),
    .B(_100_),
    .Y(_101_)
  );
  NOR _159_ (
    .A(_099_),
    .B(_101_),
    .Y(_008_)
  );
  NOT _160_ (
    .A(_008_),
    .Y(_102_)
  );
  NAND _161_ (
    .A(_098_),
    .B(_102_),
    .Y(_004_[1])
  );
  NAND _162_ (
    .A(state[0]),
    .B(reset),
    .Y(_013_)
  );
  NOT _163_ (
    .A(_013_),
    .Y(_014_)
  );
  NAND _164_ (
    .A(_095_),
    .B(_100_),
    .Y(_015_)
  );
  NOR _165_ (
    .A(_088_),
    .B(_015_),
    .Y(_016_)
  );
  NOR _166_ (
    .A(_014_),
    .B(_016_),
    .Y(_017_)
  );
  NOT _167_ (
    .A(_017_),
    .Y(_007_)
  );
  NAND _168_ (
    .A(_099_),
    .B(_017_),
    .Y(_004_[0])
  );
  NAND _169_ (
    .A(_093_),
    .B(_096_),
    .Y(_018_)
  );
  NOR _170_ (
    .A(_088_),
    .B(_018_),
    .Y(_004_[2])
  );
  NOR _171_ (
    .A(_094_),
    .B(_100_),
    .Y(_019_)
  );
  NOR _172_ (
    .A(_087_),
    .B(_019_),
    .Y(_020_)
  );
  NOR _173_ (
    .A(state[0]),
    .B(_020_),
    .Y(_003_)
  );
  NOR _174_ (
    .A(f_code[3]),
    .B(reset),
    .Y(_021_)
  );
  NOT _175_ (
    .A(_021_),
    .Y(_002_[3])
  );
  NOR _176_ (
    .A(reset),
    .B(f_code[0]),
    .Y(_022_)
  );
  NOT _177_ (
    .A(_022_),
    .Y(_002_[0])
  );
  NOR _178_ (
    .A(reset),
    .B(f_code[2]),
    .Y(_023_)
  );
  NOT _179_ (
    .A(_023_),
    .Y(_002_[2])
  );
  NOR _180_ (
    .A(reset),
    .B(f_code[1]),
    .Y(_024_)
  );
  NOT _181_ (
    .A(_024_),
    .Y(_002_[1])
  );
  NAND _182_ (
    .A(_050_),
    .B(_086_),
    .Y(_025_)
  );
  NOR _183_ (
    .A(_100_),
    .B(_025_),
    .Y(_026_)
  );
  NAND _184_ (
    .A(_011_),
    .B(_095_),
    .Y(_027_)
  );
  NAND _185_ (
    .A(_026_),
    .B(_027_),
    .Y(_028_)
  );
  NAND _186_ (
    .A(_012_),
    .B(_101_),
    .Y(_029_)
  );
  NAND _187_ (
    .A(_086_),
    .B(_029_),
    .Y(_030_)
  );
  NOR _188_ (
    .A(_097_),
    .B(_030_),
    .Y(_031_)
  );
  NOR _189_ (
    .A(state[0]),
    .B(_031_),
    .Y(_032_)
  );
  NOT _190_ (
    .A(_032_),
    .Y(_033_)
  );
  NOR _191_ (
    .A(_028_),
    .B(_033_),
    .Y(_034_)
  );
  NOR _192_ (
    .A(_018_),
    .B(_025_),
    .Y(_035_)
  );
  NOT _193_ (
    .A(_035_),
    .Y(_036_)
  );
  NAND _194_ (
    .A(_028_),
    .B(_036_),
    .Y(_037_)
  );
  NOR _195_ (
    .A(_032_),
    .B(_037_),
    .Y(_038_)
  );
  NOR _196_ (
    .A(_034_),
    .B(_038_),
    .Y(_039_)
  );
  NOR _197_ (
    .A(counter[4]),
    .B(_039_),
    .Y(_040_)
  );
  NAND _198_ (
    .A(counter[4]),
    .B(reset),
    .Y(_041_)
  );
  NOT _199_ (
    .A(_041_),
    .Y(_042_)
  );
  NAND _200_ (
    .A(_039_),
    .B(_042_),
    .Y(_043_)
  );
  NOT _201_ (
    .A(_043_),
    .Y(_000_[4])
  );
  NAND _202_ (
    .A(reset),
    .B(_040_),
    .Y(_044_)
  );
  NAND _203_ (
    .A(_043_),
    .B(_044_),
    .Y(_000_[0])
  );
  NOR _204_ (
    .A(error_sint),
    .B(_039_),
    .Y(_045_)
  );
  NAND _205_ (
    .A(_053_),
    .B(_039_),
    .Y(_046_)
  );
  NAND _206_ (
    .A(reset),
    .B(_046_),
    .Y(_047_)
  );
  NOR _207_ (
    .A(_045_),
    .B(_047_),
    .Y(_001_)
  );
  NOR _208_ (
    .A(state[0]),
    .B(_026_),
    .Y(_009_)
  );
  NAND _209_ (
    .A(_095_),
    .B(_026_),
    .Y(_010_)
  );
  DFF _210_ (
    .C(clk),
    .D(_005_),
    .Q(state[0])
  );
  DFF _211_ (
    .C(clk),
    .D(_004_[2]),
    .Q(state[1])
  );
  DFF _212_ (
    .C(clk),
    .D(_006_),
    .Q(state[2])
  );
  DFF _213_ (
    .C(clk),
    .D(_007_),
    .Q(state[3])
  );
  DFF _214_ (
    .C(clk),
    .D(_008_),
    .Q(state[4])
  );
  (* src = "state_machine_sintetizado.v:27" *)
  DFF _215_ (
    .C(clk),
    .D(_001_),
    .Q(error_sint)
  );
  (* src = "state_machine_sintetizado.v:27" *)
  DFF _216_ (
    .C(clk),
    .D(_004_[0]),
    .Q(_011_)
  );
  (* src = "state_machine_sintetizado.v:27" *)
  DFF _217_ (
    .C(clk),
    .D(_004_[1]),
    .Q(_012_)
  );
  (* src = "state_machine_sintetizado.v:27" *)
  DFF _218_ (
    .C(clk),
    .D(_000_[0]),
    .Q(counter[4])
  );
  (* src = "state_machine_sintetizado.v:27" *)
  DFF _219_ (
    .C(clk),
    .D(_000_[4]),
    .Q(counter[4])
  );
  (* src = "state_machine_sintetizado.v:27" *)
  DFF _220_ (
    .C(clk),
    .D(_002_[0]),
    .Q(f_code[0])
  );
  (* src = "state_machine_sintetizado.v:27" *)
  DFF _221_ (
    .C(clk),
    .D(_002_[1]),
    .Q(f_code[1])
  );
  (* src = "state_machine_sintetizado.v:27" *)
  DFF _222_ (
    .C(clk),
    .D(_002_[2]),
    .Q(f_code[2])
  );
  (* src = "state_machine_sintetizado.v:27" *)
  DFF _223_ (
    .C(clk),
    .D(_002_[3]),
    .Q(f_code[3])
  );
  (* src = "state_machine_sintetizado.v:47" *)
  \$_DLATCH_P_  _224_ (
    .D(1'h0),
    .E(_009_),
    .Q(counter[4])
  );
  (* src = "state_machine_sintetizado.v:47" *)
  \$_DLATCH_P_  _225_ (
    .D(_003_),
    .E(_010_),
    .Q(next_error_sint)
  );
  assign _000_[3:1] = { _000_[4], _000_[4], _000_[4] };
  assign _004_[4:3] = 2'h0;
  assign buffer = data_bus[3:0];
  assign control_out_sint = 4'h0;
  assign counter[3:0] = { counter[4], counter[4], counter[4], counter[4] };
  assign data_out_bus_sint = 16'h0000;
  assign next_state[4:3] = 2'h0;
endmodule

tarea7/probador.v
module probador#(parameter BUS_SIZE = 16,
					parameter WORD_SIZE = 4,
					parameter WORD_NUM = BUS_SIZE / WORD_SIZE
					)(
					input [BUS_SIZE-1:0] data_out_bus,
					input [WORD_NUM-1:0] control_out,
					input error,
					input [BUS_SIZE-1:0] data_out_bus_sint,
					input [WORD_NUM-1:0] control_out_sint,
					input error_sint,
					input check_control,
					input check_error, 
					input check_out,
					output reg reset,
					output reg clk, 
					output reg [BUS_SIZE-1:0] data_bus
					);

	initial begin
		$dumpfile("ss.vcd");
		$dumpvars;
		data_bus <= 16'h0000;
		reset <= 0;
		@(posedge clk);
		@(posedge clk);
		@(posedge clk);
		data_bus <= 16'hFBA0;
		reset <= 1;
		repeat (2) begin
			@(posedge clk);	
			data_bus <= data_bus + 1;
		end
		@(posedge clk);
		data_bus <= 16'hABA3;
		@(posedge clk);
		data_bus <= 16'hFBA0;
		@(posedge clk);
		data_bus <= 16'hFBA9;
		repeat (4) begin
			@(posedge clk);
		end
		
		$finish;
	end

	initial	clk 	<= 1;
	always	#15 clk 	<= ~clk;
endmodule

tarea7/state_machine.v
module state_machine #(parameter BUS_SIZE = 16,
					parameter WORD_SIZE = 4,
					parameter WORD_NUM = BUS_SIZE / WORD_SIZE
					)(
					input reset,
					input clk,
					input [BUS_SIZE-1:0] data_bus,
					output reg [BUS_SIZE-1:0] data_out_bus,
					output reg [WORD_NUM-1:0] control_out,
					output reg error
					);
	
	//Hay 13 estados: reset, first, reg, f_error inicio palabra y seq_error de secuencia
	reg [4:0] next_state, state;
	reg [WORD_SIZE:0] counter;
	reg next_error;
	integer i;
	reg [WORD_SIZE-1:0] buffer, f_code, buf2;
	reg prueba;

	parameter RESET = 0;
	parameter FIRST_PKT = 1;
	parameter REG_PKT = 2;
	parameter F_ERR = 3;
	parameter SEQ_ERR = 4;

	always @(posedge clk) begin
		if(reset == 0) begin
			state <= RESET;
			data_out_bus <= 0;
			i <= 0;
			control_out <= 0;
			error <= 0;
			counter <= 0;
		end
		else begin
			for (i = 0; i < WORD_SIZE; i=i+1) begin
				f_code[i] <= 1;
			end

			state <= next_state;
			if (next_state == FIRST_PKT || next_state == REG_PKT) counter <= counter + 1;
			else error <= next_error;
		end
	end

	always @(*) begin		//Lógica combinacional que saca el próximo estado
		next_state = state;
		buffer = data_bus[3:0];//[BUS_SIZE-1:(BUS_SIZE-WORD_SIZE)];
		//if (state == RESET) begin 		//Acá no se puede manipular reset, intefiere
		//	next_state = FIRST_PKT;
		//	next_error = 0;
		//end
		case(state)
			RESET: begin
				next_state = FIRST_PKT;
				next_error = 0;
			end
			FIRST_PKT:
			begin
				if(data_bus[BUS_SIZE-1:(BUS_SIZE-WORD_SIZE)] == f_code) begin
					if(data_bus[3:0] == counter) begin
						next_state = REG_PKT;
						next_error = 0;
					end
					else next_state = SEQ_ERR;
				end
				else begin
					next_state = F_ERR;
					next_error = 1;
				end
			end
			REG_PKT: 
			begin						// Revisar si empieza en F y termina entre [1-9] dep contador
				if (data_bus[3:0] == counter) begin
					next_state = REG_PKT;
					next_error = 0;
				end
				else begin
					next_state = SEQ_ERR;
					next_error = 1;
				end
			end
			F_ERR: 
			begin
				next_state = FIRST_PKT;
				next_error = 0;
				counter = 0;
			end
			SEQ_ERR:
			begin
				next_state = FIRST_PKT;
				next_error = 0;
				counter = 0;
			end		
		endcase
		else if (data_bus[BUS_SIZE-1:(BUS_SIZE-WORD_SIZE)] != f_code) begin
			next_state = F_ERR;
			next_error = 1;
			counter = 0;
		end
	end
endmodule

tarea7/generate_mod_sintetizado.v
/* Generated by Yosys 0.9 (git sha1 1979e0b) */

(* dynports =  1  *)
(* cells_not_processed =  1  *)
(* src = "buffer_gen_sintetizado.v:1" *)
module buffer_gen_sintetizado(clk, data_bus, data_out_bus_sint, control_out_sint);
  (* src = "buffer_gen_sintetizado.v:11" *)
  wire _00_;
  wire _01_;
  wire _02_;
  (* src = "buffer_gen_sintetizado.v:5" *)
  input clk;
  (* src = "buffer_gen_sintetizado.v:8" *)
  output control_out_sint;
  (* src = "buffer_gen_sintetizado.v:6" *)
  input [3:0] data_bus;
  (* src = "buffer_gen_sintetizado.v:7" *)
  output [3:0] data_out_bus_sint;
  NOR _03_ (
    .A(data_bus[2]),
    .B(data_bus[3]),
    .Y(_01_)
  );
  NOR _04_ (
    .A(data_bus[0]),
    .B(data_bus[1]),
    .Y(_02_)
  );
  NAND _05_ (
    .A(_01_),
    .B(_02_),
    .Y(_00_)
  );
  (* src = "buffer_gen_sintetizado.v:11" *)
  DFF _06_ (
    .C(clk),
    .D(data_bus[0]),
    .Q(data_out_bus_sint[0])
  );
  (* src = "buffer_gen_sintetizado.v:11" *)
  DFF _07_ (
    .C(clk),
    .D(data_bus[1]),
    .Q(data_out_bus_sint[1])
  );
  (* src = "buffer_gen_sintetizado.v:11" *)
  DFF _08_ (
    .C(clk),
    .D(data_bus[2]),
    .Q(data_out_bus_sint[2])
  );
  (* src = "buffer_gen_sintetizado.v:11" *)
  DFF _09_ (
    .C(clk),
    .D(data_bus[3]),
    .Q(data_out_bus_sint[3])
  );
  (* src = "buffer_gen_sintetizado.v:11" *)
  DFF _10_ (
    .C(clk),
    .D(_00_),
    .Q(control_out_sint)
  );
endmodule

(* dynports =  1  *)
(* cells_not_processed =  1  *)
(* src = "generate_mod_sintetizado.v:3" *)
module generate_mod_sintetizado(data_bus, clk, data_out_bus_sint, control_out_sint);
  (* src = "generate_mod_sintetizado.v:8" *)
  input clk;
  (* src = "generate_mod_sintetizado.v:10" *)
  output [3:0] control_out_sint;
  (* src = "generate_mod_sintetizado.v:7" *)
  input [15:0] data_bus;
  (* src = "generate_mod_sintetizado.v:9" *)
  output [15:0] data_out_bus_sint;
  (* module_not_derived = 32'd1 *)
  (* src = "generate_mod_sintetizado.v:16" *)
  buffer_gen_sintetizado \BUFFER_GEN_1[0].buff  (
    .clk(clk),
    .control_out_sint(control_out_sint[3]),
    .data_bus(data_bus[3:0]),
    .data_out_bus_sint(data_out_bus_sint[15:12])
  );
  (* module_not_derived = 32'd1 *)
  (* src = "generate_mod_sintetizado.v:16" *)
  buffer_gen_sintetizado \BUFFER_GEN_1[1].buff  (
    .clk(clk),
    .control_out_sint(control_out_sint[2]),
    .data_bus(data_bus[7:4]),
    .data_out_bus_sint(data_out_bus_sint[11:8])
  );
  (* module_not_derived = 32'd1 *)
  (* src = "generate_mod_sintetizado.v:16" *)
  buffer_gen_sintetizado \BUFFER_GEN_1[2].buff  (
    .clk(clk),
    .control_out_sint(control_out_sint[1]),
    .data_bus(data_bus[11:8]),
    .data_out_bus_sint(data_out_bus_sint[7:4])
  );
  (* module_not_derived = 32'd1 *)
  (* src = "generate_mod_sintetizado.v:16" *)
  buffer_gen_sintetizado \BUFFER_GEN_1[3].buff  (
    .clk(clk),
    .control_out_sint(control_out_sint[0]),
    .data_bus(data_bus[15:12]),
    .data_out_bus_sint(data_out_bus_sint[3:0])
  );
endmodule

tarea7/buffer_gen.v
module buffer_gen # (parameter BUS_SIZE = 16,
					parameter WORD_SIZE = 4,
					parameter WORD_NUM = BUS_SIZE / WORD_SIZE
					)(
					input clk,
					input [WORD_SIZE-1:0] data_bus,
					output reg [WORD_SIZE-1:0] data_out_bus,
					output reg control_out
					);
		
	always @(posedge clk) begin
		if (data_bus == 0) begin
			control_out <= 0;
		end
		else control_out <= 1;
		data_out_bus <= data_bus;
	end

endmodule

tarea7/generate_mod.v
`include "buffer_gen.v"

module generate_mod # (
	parameter BUS_SIZE = 16,
    parameter WORD_SIZE = 4,
    parameter WORD_NUM = BUS_SIZE/WORD_SIZE)
	(input [BUS_SIZE-1:0] data_bus,
	input clk,
	output [BUS_SIZE-1:0] data_out_bus,
	output [WORD_NUM-1:0] control_out
	);

	genvar i;
	generate
	for (i = 0; i < WORD_NUM; i = i+1) begin: BUFFER_GEN_1
		buffer_gen buff (.data_bus(data_bus[i*WORD_SIZE +: WORD_SIZE]),
						.clk (clk),
						.data_out_bus (data_out_bus[(BUS_SIZE-1)-(WORD_SIZE*i): (BUS_SIZE	)-(WORD_SIZE*(i+1))]),
						.control_out (control_out[WORD_NUM-i-1])
						);
	end
	endgenerate
endmodule

tarea7/bancopruebas.v
`include "probador.v"
`include "state_machine.v"
`include "state_machine_sintetizado.v"
`include "generate_mod.v"
`include "./lib/cmos_cells.v"
`include "generate_mod_sintetizado.v"
`include "checker.v"

module bancopruebas();
    parameter BUS_SIZE = 16;
    parameter WORD_SIZE = 4;
    parameter WORD_NUM = BUS_SIZE/WORD_SIZE;

    wire [BUS_SIZE-1:0] data_bus;
    wire [BUS_SIZE-1:0] data_out_bus, data_out_bus_sint;
    wire [WORD_NUM-1:0] control_out, control_out_sint;
    wire error, error_sint, check_control, check_error, check_out;

generate_mod#(
    .BUS_SIZE     ( 16 ),
    .WORD_SIZE    ( 4 ),
    .WORD_NUM     ( BUS_SIZE/WORD_SIZE )
)u_generate_mod(
    .data_bus     ( data_bus [BUS_SIZE-1:0]    ),
    .clk          (clk                          ),
    .data_out_bus ( data_out_bus [BUS_SIZE-1:0] ),
    .control_out  ( control_out [WORD_NUM-1:0]  )
);

generate_mod_sintetizado #(
    .BUS_SIZE (16),
    .WORD_SIZE(4),
    .WORD_NUM (BUS_SIZE/WORD_SIZE)
)generate_mod_sintetizado_1(
    .data_bus (data_bus[BUS_SIZE-1:0]),
    .clk      (clk),
    .data_out_bus_sint (data_out_bus_sint [BUS_SIZE-1:0]),
    .control_out_sint (control_out_sint [WORD_NUM-1:0])
);


state_machine #(
    .BUS_SIZE     ( 16 ),
    .WORD_SIZE    ( 4 ),
    .WORD_NUM     ( BUS_SIZE/WORD_SIZE )
    ) u_state_machine (
    .reset        ( reset        ),
    .clk          ( clk          ),
    .data_bus     ( data_bus [BUS_SIZE-1:0] ),
    .error        ( error        )
);

probador u_probador(
    .data_out_bus ( data_out_bus [BUS_SIZE-1:0]),
    .control_out  ( control_out [WORD_NUM-1:0]  ),
    .error        ( error        ),
    .data_out_bus_sint ( data_out_bus_sint [BUS_SIZE-1:0]),
    .control_out_sint  ( control_out_sint [WORD_NUM-1:0]  ),
    .error_sint        ( error_sint        ),
    .reset        ( reset        ),
    .clk          ( clk          ),
    .data_bus     ( data_bus  [BUS_SIZE-1:0]),
    .check_control (check_control),
    .check_error ( check_error),
    .check_out (check_out)
);

state_machine_sintetizado #(
    .BUS_SIZE     ( 16 ),
    .WORD_SIZE    ( 4 ),
    .WORD_NUM     ( BUS_SIZE/WORD_SIZE )
    ) u_state_machine_sint (
    .reset        ( reset ),
    .clk          ( clk   ),
    .data_bus     ( data_bus [BUS_SIZE-1:0] ),
    .error_sint        ( error_sint  )
);

checker#(
    .BUS_SIZE          ( BUS_SIZE ),
    .WORD_SIZE         ( WORD_SIZE ),
    .WORD_NUM          ( BUS_SIZE/WORD_SIZE )
)u_checker(
    .error             ( error             ),
    .error_sint        ( error_sint        ),
    .data_out_bus      ( data_out_bus      ),
    .data_out_bus_sint ( data_out_bus_sint ),
    .control_out       ( control_out       ),
    .control_out_sint  ( control_out_sint  ),
    .check_out         ( check_out         ),
    .check_control     ( check_control     ),
    .check_error       ( check_error       )
);



endmodule

tarea7/ss.vcd
$date
	Sun Oct 11 19:15:28 2020
$end
$version
	Icarus Verilog
$end
$timescale
	1s
$end
$scope module bancopruebas $end
$var wire 1 ! reset $end
$var wire 1 " error $end
$var wire 16 # data_out_bus [15:0] $end
$var wire 16 $ data_bus [15:0] $end
$var wire 4 % control_out [3:0] $end
$var wire 1 & clk $end
$scope module u_probador $end
$var wire 1 " error $end
$var wire 16 ' data_out_bus [15:0] $end
$var wire 4 ( control_out [3:0] $end
$var reg 1 & clk $end
$var reg 16 ) data_bus [15:0] $end
$var reg 1 ! reset $end
$upscope $end
$scope module u_state_machine $end
$var wire 1 & clk $end
$var wire 16 * data_bus [15:0] $end
$var wire 1 ! reset $end
$var reg 4 + buffer [3:0] $end
$var reg 4 , control_out [3:0] $end
$var reg 5 - counter [4:0] $end
$var reg 16 . data_out_bus [15:0] $end
$var reg 1 " error $end
$var reg 4 / f_code [3:0] $end
$var reg 1 0 next_error $end
$var reg 5 1 next_state [4:0] $end
$var reg 5 2 state [4:0] $end
$var integer 32 3 i [31:0] $end
$upscope $end
$upscope $end
$enddefinitions $end
#0
$dumpvars
bx 3
bx 2
bx 1
x0
bx /
bx .
bx -
bx ,
b0 +
b0 *
b0 )
bx (
bx '
0&
bx %
b0 $
bx #
x"
0!
$end
#15
00
b1 1
b0 -
0"
b0 %
b0 (
b0 ,
b0 3
b0 #
b0 '
b0 .
b0 2
1&
#30
0&
#45
b1 1
1!
b1111101110100000 $
b1111101110100000 )
b1111101110100000 *
1&
#60
0&
#75
b1 +
b1 2
b1111101110100001 $
b1111101110100001 )
b1111101110100001 *
b10 1
b1 -
b100 3
b1111 /
1&
#90
0&
#105
b10 +
b1111101110100010 $
b1111101110100010 )
b1111101110100010 *
b10 2
00
b10 1
b10 -
b100 3
1&
#120
0&
#135
b11 +
b1010101110100011 $
b1010101110100011 )
b1010101110100011 *
10
b11 1
b0 -
b100 3
1&
#150
0&
#165
00
b1 1
b0 +
b1111101110100000 $
b1111101110100000 )
b1111101110100000 *
b11 2
1"
b100 3
1&
#180
0&
#195
10
b1001 +
b1 2
b1111101110101001 $
b1111101110101001 )
b1111101110101001 *
b100 1
b0 -
b100 3
1&
#210
0&
#225
00
b1 1
b100 2
b100 3
1&
#240
0&
#255
10
b1 2
b100 1
b0 -
b100 3
1&
#270
0&
#285
00
b1 1
b100 2
b100 3
1&
#300
0&
#315
10
b1 2
b100 1
b0 -
b100 3
1&
