tarea2/probador_mux.v
module probador_mux(input [0:1] data_out,
		    output reg reset_L,
		    output reg [0:1] data_in0,
		    output reg [0:1] data_in1,
		    output reg selector,
		    output reg clk);
   initial begin
      $dumpfile("mux.vcd"); //Se depositan los datos en este archivo para leerlo en gtkwave
      $dumpvars;
      $display ("\t\t\tclk,\tdata_in0,\tdata_in1,\tdata_out,\treset_L ,\tselector");

      $monitor($time, "\t%b\t%b\t\t%b\t\t%b\t\t%b \t\t%b", clk, data_in0, data_in1, data_out, reset_L, selector); //Datos a mostar
      
      {selector, reset_L} <= 'b0; //Se inicializan estas entradas a 0
      {data_in0, data_in1} <= 2'b00; //Se inicializan entradas en 00



      @(posedge clk); //Como los pulsos no siguen una secuencia, se deben generar uno por uno en cada flanco
      reset_L <= 1;

      @(posedge clk);
      data_in0 <= 2'b11;
      data_in1 <= 2'b10;

      @(posedge clk);
      selector <= 1;
      data_in0 <= 2'b01;
      data_in1 <= 2'b00;

      @(posedge clk);
      data_in0 <= 2'b00;
      data_in1 <= 2'b10;

      @(posedge clk);
      selector <= 0;
      data_in0 <= 2'b11; 
      data_in1 <= 2'b11;

      @(posedge clk);
      selector <= 1;
      data_in0 <= 2'b00;
      data_in1 <= 2'b01;

      @(posedge clk);
      selector <= 0;
      data_in0 <= 2'b10;
      data_in1 <= 2'b00;

      @(posedge clk);

      @(posedge clk); //Para mostrar dos ciclo más
      
      
$finish;
      
   end // initial begin
  
   initial clk <= 0;
   always #2 clk <= ~clk;

endmodule // probador_mux

tarea5/mux.v
module mux(input clk,
	   input 	    reset_L,
	   input 	    selector,
	   input [1:0] 	    data_in0,
	   input [1:0] 	    data_in1,
	   output reg [1:0] data_out);

   reg [1:0] salMux1 = 2'b00; //se genera un elemento para conexión capaz de almacenar datos
   
   
   always @(*) begin
      salMux1 = 1'b0; //se inicializa el valor de conexión a 0
      if (selector == 0)
	salMux1 = data_in0; //Dependiendo del valor del selector, se pasa a la salida del mux
      else
	salMux1 = data_in1;
   end

   always @(posedge clk) begin //Se hace otro elemento que lee únicamente en el flanco positivo de reloj, este elemento resetea o deja pasar el dato y lo guarda

      if (reset_L == 0)
	data_out <= 2'b00; //Si reset_L esta en 0 se resetea, caso contrario se pasa el dato del primer mux 
      else
	data_out <= salMux1;
   end
endmodule

tarea3-4/BancoPruebaConductual_mux.v
`timescale 1s / 1ms

`include "mux.v"
`include "probador_mux.v"

module BancoPruebas;
   wire [1:0] data_in0, data_in1, data_out; //Se generan los cables de entrada (buses)
   wire       clk, salMux1, reset_L, selector; 
   

   
   mux p_cond(/*AUTOINST*/
	      // Outputs
	      .data_out			(data_out[1:0]),
	      // Inputs
	      .clk			(clk),
	      .reset_L			(reset_L),
	      .selector			(selector),
	      .data_in0			(data_in0[1:0]),
	      .data_in1			(data_in1[1:0]));
   
   
   probador_mux probador(/*AUTOINST*/
			 // Outputs
			 .reset_L		(reset_L),
			 .data_in0		(data_in0[1:0]),
			 .data_in1		(data_in1[1:0]),
			 .selector		(selector),
			 .clk			(clk),
			 // Inputs
			 .data_out		(data_out[1:0]));
   

endmodule

tarea2/mux.vcd
$date
	Tue Sep  8 12:37:33 2020
$end
$version
	Icarus Verilog
$end
$timescale
	1ms
$end
$scope module BancoPruebas $end
$var wire 1 ! selector $end
$var wire 1 " reset_L $end
$var wire 2 # data_out [1:0] $end
$var wire 2 $ data_in1 [1:0] $end
$var wire 2 % data_in0 [1:0] $end
$var wire 1 & clk $end
$scope module p_cond $end
$var wire 1 ! selector $end
$var wire 1 " reset_L $end
$var wire 2 ' data_in1 [1:0] $end
$var wire 2 ( data_in0 [1:0] $end
$var wire 1 & clk $end
$var reg 2 ) data_out [1:0] $end
$var reg 2 * salMux1 [1:0] $end
$upscope $end
$scope module probador $end
$var wire 2 + data_out [0:1] $end
$var reg 1 & clk $end
$var reg 2 , data_in0 [0:1] $end
$var reg 2 - data_in1 [0:1] $end
$var reg 1 " reset_L $end
$var reg 1 ! selector $end
$upscope $end
$upscope $end
$enddefinitions $end
#0
$dumpvars
b0 -
b0 ,
bx +
b0 *
bx )
b0 (
b0 '
0&
b0 %
b0 $
bx #
0"
0!
$end
#2000
b0 #
b0 )
b0 +
1"
1&
#4000
0&
#6000
b11 *
b10 $
b10 '
b10 -
b11 %
b11 (
b11 ,
1&
#8000
0&
#10000
b0 *
b11 #
b11 )
b11 +
b0 $
b0 '
b0 -
b1 %
b1 (
b1 ,
1!
1&
#12000
0&
#14000
b10 *
b10 $
b10 '
b10 -
b0 %
b0 (
b0 ,
b0 #
b0 )
b0 +
1&
#16000
0&
#18000
b11 *
b10 #
b10 )
b10 +
b11 $
b11 '
b11 -
b11 %
b11 (
b11 ,
0!
1&
#20000
0&
#22000
b1 *
b1 $
b1 '
b1 -
b0 %
b0 (
b0 ,
1!
b11 #
b11 )
b11 +
1&
#24000
0&
#26000
b10 *
b1 #
b1 )
b1 +
b0 $
b0 '
b0 -
b10 %
b10 (
b10 ,
0!
1&
#28000
0&
#30000
b10 #
b10 )
b10 +
1&
