tarea6/src/mux2a1_2b/sintetizado2a1_cmos.v
/* Generated by Yosys 0.9 (git sha1 1979e0b) */

(* top =  1  *)
(* src = "./src/sintetizado2a1_cmos/sintetizado2a1_cmos.v:1" *)
module sintetizado2a1_cmos(clk, reset_L, selector, valid_0, valid_1, data_in0, data_in1, valid_out_estructural, data_estructural);
  (* src = "./src/sintetizado2a1_cmos/sintetizado2a1_cmos.v:26" *)
  wire [1:0] _00_;
  (* src = "./src/sintetizado2a1_cmos/sintetizado2a1_cmos.v:26" *)
  wire _01_;
  wire _02_;
  wire _03_;
  wire _04_;
  wire _05_;
  wire _06_;
  wire _07_;
  wire _08_;
  wire _09_;
  wire _10_;
  wire _11_;
  wire _12_;
  wire _13_;
  wire _14_;
  wire _15_;
  wire _16_;
  wire _17_;
  wire _18_;
  wire _19_;
  wire _20_;
  wire _21_;
  wire _22_;
  (* src = "./src/sintetizado2a1_cmos/sintetizado2a1_cmos.v:1" *)
  input clk;
  (* src = "./src/sintetizado2a1_cmos/sintetizado2a1_cmos.v:9" *)
  output [1:0] data_estructural;
  (* src = "./src/sintetizado2a1_cmos/sintetizado2a1_cmos.v:6" *)
  input [1:0] data_in0;
  (* src = "./src/sintetizado2a1_cmos/sintetizado2a1_cmos.v:7" *)
  input [1:0] data_in1;
  (* src = "./src/sintetizado2a1_cmos/sintetizado2a1_cmos.v:2" *)
  input reset_L;
  (* init = 2'h0 *)
  (* src = "./src/sintetizado2a1_cmos/sintetizado2a1_cmos.v:11" *)
  (* unused_bits = "0 1" *)
  wire [1:0] salMux1;
  (* src = "./src/sintetizado2a1_cmos/sintetizado2a1_cmos.v:3" *)
  input selector;
  (* src = "./src/sintetizado2a1_cmos/sintetizado2a1_cmos.v:4" *)
  input valid_0;
  (* src = "./src/sintetizado2a1_cmos/sintetizado2a1_cmos.v:5" *)
  input valid_1;
  (* src = "./src/sintetizado2a1_cmos/sintetizado2a1_cmos.v:8" *)
  output valid_out_estructural;
  NAND _23_ (
    .A(_11_),
    .B(_12_),
    .Y(_13_)
  );
  NOR _24_ (
    .A(_10_),
    .B(_13_),
    .Y(_14_)
  );
  NAND _25_ (
    .A(_03_),
    .B(_10_),
    .Y(_15_)
  );
  NAND _26_ (
    .A(reset_L),
    .B(_15_),
    .Y(_16_)
  );
  NOR _27_ (
    .A(_14_),
    .B(_16_),
    .Y(_00_[0])
  );
  NAND _28_ (
    .A(selector),
    .B(data_in1[1]),
    .Y(_17_)
  );
  NAND _29_ (
    .A(_02_),
    .B(data_in0[1]),
    .Y(_18_)
  );
  NAND _30_ (
    .A(_17_),
    .B(_18_),
    .Y(_19_)
  );
  NOR _31_ (
    .A(_10_),
    .B(_19_),
    .Y(_20_)
  );
  NAND _32_ (
    .A(_04_),
    .B(_10_),
    .Y(_21_)
  );
  NAND _33_ (
    .A(reset_L),
    .B(_21_),
    .Y(_22_)
  );
  NOR _34_ (
    .A(_20_),
    .B(_22_),
    .Y(_00_[1])
  );
  NOR _35_ (
    .A(_05_),
    .B(_10_),
    .Y(_01_)
  );
  NOT _36_ (
    .A(selector),
    .Y(_02_)
  );
  NOT _37_ (
    .A(data_estructural[0]),
    .Y(_03_)
  );
  NOT _38_ (
    .A(data_estructural[1]),
    .Y(_04_)
  );
  NOT _39_ (
    .A(reset_L),
    .Y(_05_)
  );
  NOT _40_ (
    .A(valid_0),
    .Y(_06_)
  );
  NAND _41_ (
    .A(selector),
    .B(valid_1),
    .Y(_07_)
  );
  NOT _42_ (
    .A(_07_),
    .Y(_08_)
  );
  NOR _43_ (
    .A(selector),
    .B(_06_),
    .Y(_09_)
  );
  NOR _44_ (
    .A(_08_),
    .B(_09_),
    .Y(_10_)
  );
  NAND _45_ (
    .A(selector),
    .B(data_in1[0]),
    .Y(_11_)
  );
  NAND _46_ (
    .A(_02_),
    .B(data_in0[0]),
    .Y(_12_)
  );
  (* src = "./src/sintetizado2a1_cmos/sintetizado2a1_cmos.v:26" *)
  DFF _47_ (
    .C(clk),
    .D(_01_),
    .Q(valid_out_estructural)
  );
  (* src = "./src/sintetizado2a1_cmos/sintetizado2a1_cmos.v:26" *)
  DFF _48_ (
    .C(clk),
    .D(_00_[0]),
    .Q(data_estructural[0])
  );
  (* src = "./src/sintetizado2a1_cmos/sintetizado2a1_cmos.v:26" *)
  DFF _49_ (
    .C(clk),
    .D(_00_[1]),
    .Q(data_estructural[1])
  );
endmodule

tarea6/src/probador_mux.v
module probador_mux(input [3:0] data_conductual,
         input [3:0] data_estructural,
         input valid_out_conductual,
         input valid_out_estructural,
         output reg valid_0,
         output reg valid_1,
         output reg valid_2,
         output reg valid_3,
         output reg reset_L,
         output reg [3:0] data_in0,
         output reg [3:0] data_in1,
         output reg [3:0] data_in2,
         output reg [3:0] data_in3,
         output reg [1:0] selector,
         output reg clk);
   initial begin
      $dumpfile("mux.vcd"); //Se depositan los datos en este archivo para leerlo en gtkwave
      $dumpvars;
      //$display ("\t\t\tclk,\tdata_in0,\tdata_in1,\tdata_out,\treset_L ,\tselector");

      //$monitor($time, "\t%b\t%b\t\t%b\t\t%b\t\t%b \t\t%b", clk, data_in0, data_in1, data_out, reset_L, selector); //Datos a mostar
      selector <= 2'b00;
      reset_L <= 'b0; //Se inicializan estas entradas a 0
      {data_in0, data_in1, data_in2, data_in3} <= 4'b0000; //Se inicializan entradas en 00
      {valid_0, valid_1, valid_2, valid_3} <= 0;
      
      @(posedge clk); //Como los pulsos no siguen una secuencia, se deben generar uno por uno en cada flanco
      reset_L <= 1;
      selector <= 2'b01;
      data_in0 <= 1101;
      valid_1 <= 0;
      valid_0 <= 1;
      valid_2 <= 0;
      valid_3 <= 1;

      @(posedge clk);
      selector <= 2'b01;
      data_in1 <= 4'b1010;
      data_in0 <= 4'b1101;
      data_in2 <= 4'b0100;
      data_in3 <= 4'b0011;
      valid_1 <= 1;
      valid_0 <= 1;
      valid_2 <= 0;
      valid_3 <= 0;

      @(posedge clk);
      selector <= 2'b10;
      data_in0 <= 4'b0101;
      data_in1 <= 4'b1000;
      data_in2 <= 4'b1110;
      data_in3 <= 4'b1111;
      valid_1 <= 0;
      valid_0 <= 1;
      valid_2 <= 1;
      valid_3 <= 1;

      @(posedge clk);
      selector <= 2'b11;
      data_in0 <= 4'b0100;
      data_in1 <= 4'b1001;
      data_in2 <= 4'b1010;
      data_in3 <= 4'b1011;
      valid_1 <= 1;
      valid_0 <= 1;
      valid_2 <= 1;
      valid_3 <= 0;

      @(posedge clk);
      valid_1 <= 1;
      valid_0 <= 1;
      valid_2 <= 0;
      valid_3 <= 1;
      selector <= 2'b01;
      data_in0 <= 4'b0111; 
      data_in1 <= 4'b1011;
      data_in2 <= 4'b1110;
      data_in3 <= 4'b0011;


      @(posedge clk);
      selector <= 1;
      data_in0 <= 4'b0100;
      data_in1 <= 4'b0101;
      data_in2 <= 4'b1000;
      data_in3 <= 4'b1111;
      selector <= 2'b10;
      valid_1 <= 0;
      valid_0 <= 1;
      valid_2 <= 0;
      valid_3 <= 1;

      @(posedge clk);
      selector <= 0;
      data_in0 <= 4'b1010;
      data_in1 <= 4'b0000;
      data_in2 <= 4'b1001;
      data_in3 <= 4'b1011;
      selector <= 2'b10;
      valid_1 <= 1;
      valid_0 <= 1;
      valid_2 <= 1;
      valid_3 <= 1;

      @(posedge clk);

      @(posedge clk);

      @(posedge clk); //Para mostrar dos ciclo más
      
      
$finish;
      
   end // initial begin

   always @(posedge clk) begin
      if(data_conductual != data_estructural) begin
         $display($time, "s\tLas señales no son iguales");
      end
      if(data_conductual == data_estructural) begin
         $display($time, "s\tOK");
      end
   end

   initial clk <= 0;
   always #2 clk <= ~clk;

endmodule // probador_mux

tarea6/src/mux2a1_2b/mux2a1_2b.v
module mux2a1_2b( input clk,
            input 	    reset_L,
            input 	    selector,
            input        valid_0,
            input        valid_1,
            input [1:0] 	    data_in0,
            input [1:0] 	    data_in1,
            output reg         valid_out_conductual,
            output reg [1:0] data_conductual);

      reg [1:0] salMux1 = 2'b00;                  //se genera un elemento para conexión capaz de almacenar datos
      reg salValid;
      //Valid en 1 pasa
      always @(*) begin
            //salMux1 = 1'b0;               //se inicializa el valor de conexión a 0
            if (selector == 0) begin
                  salValid = valid_0;
	            salMux1 = data_in0;     //Dependiendo del valor del selector, se pasa a la salida del mux
            end
            else begin
                  salValid = valid_1;
                  salMux1 = data_in1;
            end
      end

      always @(posedge clk) begin         //Se hace otro elemento que lee únicamente en el flanco positivo de reloj, este elemento resetea o deja pasar el dato y lo guarda
            if (reset_L == 0) begin
	            data_conductual <= 0;          //Si reset_L esta en 0 se resetea, caso contrario se pasa el dato del primer mux 
                  valid_out_conductual <= 0; 
            end
            else begin                    //El valid afecta acá, si valid está en 1 deja pasar, si no pasa el val pasado
                  if ((selector == 0 && valid_0 == 1) || (selector == 1 && valid_1 == 1)) begin   
                        data_conductual <= salMux1;
                  end
                  valid_out_conductual <= salValid;
            end
      end
endmodule

tarea6/src/mux2a1_2b/BancoPrueba_2a1_2b.v
`timescale 1s / 1ms

`include "./src/probador_mux.v"
`include "./lib/cmos_cells.v"
`include "./src/mux2a1_2b/mux2a1_2b.v"
`include "./src/mux2a1_2b/sintetizado2a1_cmos.v"

module BancoPruebas;
	wire [1:0] data_in0, data_in1, data_conductual, data_estructural; //Se generan los cables de entrada (buses)
	wire       clk, salMux1, reset_L, selector, salValid, valid_out_conductual, valid_out_estructural; 

	mux2a1_2b p_conductal(/*AUTOINST*/
			      // Outputs
			      .valid_out_conductual	(valid_out_conductual),
			      .data_conductual	(data_conductual[1:0]),
			      // Inputs
			      .clk		(clk),
			      .reset_L		(reset_L),
			      .selector		(selector),
			      .valid_0		(valid_0),
			      .valid_1		(valid_1),
			      .data_in0		(data_in0[1:0]),
			      .data_in1		(data_in1[1:0]));

        probador_mux probador(/*AUTOINST*/
			      // Outputs
			      .valid_0		(valid_0),
			      .valid_1		(valid_1),
			      .reset_L		(reset_L),
			      .data_in0		(data_in0[1:0]),
			      .data_in1		(data_in1[1:0]),
			      .selector		(selector),
			      .clk		(clk),
			      // Inputs
			      .data_conductual	(data_conductual[1:0]),
			      .data_estructural	(data_estructural[1:0]),
			      .valid_out_conductual	(valid_out_conductual),
				  .valid_out_estructural (valid_out_estructural));

   //Para que autoinst sirva, tiene que estar en la misma carpeta
	sintetizado2a1_cmos synth_estructural(/*AUTOINST*/
					      // Outputs
					      .data_estructural	(data_estructural[1:0]),
					      .valid_out_estructural	(valid_out_estructural),
					      // Inputs
					      .clk		(clk),
					      .data_in0		(data_in0[1:0]),
					      .data_in1		(data_in1[1:0]),
					      .reset_L		(reset_L),
					      .selector		(selector),
					      .valid_0		(valid_0),
					      .valid_1		(valid_1));


endmodule

tarea5/cmos_cells_retardos.v

module BUF(A, Y);
input A;
output Y;
assign #(1.4:4.1:4.1) Y = A;
endmodule

module NOT(A, Y);
input A;
output Y;
assign #(1:3.5:6, 1:3.5:6) Y = ~A;
endmodule

module NAND(A, B, Y); //SN74LVC1G38
input A, B;
output Y;
assign #(0.9:1.6:2.4, 0.9:1.6:2.4) Y = ~(A & B);
endmodule

module NOR(A, B, Y);
input A, B;
output Y;
assign #(0.8:2.1:3.4, 0.8:2.1:3.4) Y = ~(A | B);
endmodule

module DFF(C, D, Q); //(1.1:2.4:3.8)
input C, D;
output reg Q;
always @(posedge C)
	#(1.1:2.4:3.8) Q <= D;
endmodule

module DFFSR(C, D, Q, S, R);
//assign #(1:3.5:6, 1:3.5:6)
input C, D, S, R;
output reg Q;
always @(posedge C, posedge S, posedge R)
	if (S)
		Q <= 1'b1;
	else if (R)
		Q <= 1'b0;
	else
		Q <= D;
endmodule

tarea6/mux.vcd
$date
	Thu Sep 17 11:05:22 2020
$end
$version
	Icarus Verilog
$end
$timescale
	1ms
$end
$scope module BUF $end
$var wire 1 ! A $end
$var wire 1 " Y $end
$upscope $end
$scope module BancoPruebas $end
$var wire 1 # valid_out_estructural $end
$var wire 1 $ valid_out_conductual $end
$var wire 1 % valid_1 $end
$var wire 1 & valid_0 $end
$var wire 1 ' selector $end
$var wire 1 ( reset_L $end
$var wire 2 ) data_in1 [1:0] $end
$var wire 2 * data_in0 [1:0] $end
$var wire 2 + data_estructural [1:0] $end
$var wire 2 , data_conductual [1:0] $end
$var wire 1 - clk $end
$scope module p_conductal $end
$var wire 2 . data_in0 [1:0] $end
$var wire 2 / data_in1 [1:0] $end
$var wire 1 ' selector $end
$var wire 1 % valid_1 $end
$var wire 1 & valid_0 $end
$var wire 1 ( reset_L $end
$var wire 1 - clk $end
$var reg 2 0 data_conductual [1:0] $end
$var reg 2 1 salMux1 [1:0] $end
$var reg 1 2 salValid $end
$var reg 1 $ valid_out_conductual $end
$upscope $end
$scope module probador $end
$var wire 4 3 data_conductual [3:0] $end
$var wire 4 4 data_estructural [3:0] $end
$var wire 1 $ valid_out_conductual $end
$var wire 1 # valid_out_estructural $end
$var reg 1 - clk $end
$var reg 4 5 data_in0 [3:0] $end
$var reg 4 6 data_in1 [3:0] $end
$var reg 4 7 data_in2 [3:0] $end
$var reg 4 8 data_in3 [3:0] $end
$var reg 1 ( reset_L $end
$var reg 2 9 selector [1:0] $end
$var reg 1 & valid_0 $end
$var reg 1 % valid_1 $end
$var reg 1 : valid_2 $end
$var reg 1 ; valid_3 $end
$upscope $end
$scope module synth_estructural $end
$var wire 1 - clk $end
$var wire 2 < data_in0 [1:0] $end
$var wire 2 = data_in1 [1:0] $end
$var wire 1 ( reset_L $end
$var wire 1 ' selector $end
$var wire 1 & valid_0 $end
$var wire 1 % valid_1 $end
$var wire 1 # valid_out_estructural $end
$var wire 2 > data_estructural [1:0] $end
$var wire 1 ? _22_ $end
$var wire 1 @ _21_ $end
$var wire 1 A _20_ $end
$var wire 1 B _19_ $end
$var wire 1 C _18_ $end
$var wire 1 D _17_ $end
$var wire 1 E _16_ $end
$var wire 1 F _15_ $end
$var wire 1 G _14_ $end
$var wire 1 H _13_ $end
$var wire 1 I _12_ $end
$var wire 1 J _11_ $end
$var wire 1 K _10_ $end
$var wire 1 L _09_ $end
$var wire 1 M _08_ $end
$var wire 1 N _07_ $end
$var wire 1 O _06_ $end
$var wire 1 P _05_ $end
$var wire 1 Q _04_ $end
$var wire 1 R _03_ $end
$var wire 1 S _02_ $end
$var wire 1 T _01_ $end
$var wire 2 U _00_ [1:0] $end
$scope module _23_ $end
$var wire 1 H Y $end
$var wire 1 I B $end
$var wire 1 J A $end
$upscope $end
$scope module _24_ $end
$var wire 1 H B $end
$var wire 1 G Y $end
$var wire 1 K A $end
$upscope $end
$scope module _25_ $end
$var wire 1 F Y $end
$var wire 1 K B $end
$var wire 1 R A $end
$upscope $end
$scope module _26_ $end
$var wire 1 ( A $end
$var wire 1 F B $end
$var wire 1 E Y $end
$upscope $end
$scope module _27_ $end
$var wire 1 G A $end
$var wire 1 E B $end
$var wire 1 V Y $end
$upscope $end
$scope module _28_ $end
$var wire 1 ' A $end
$var wire 1 W B $end
$var wire 1 D Y $end
$upscope $end
$scope module _29_ $end
$var wire 1 X B $end
$var wire 1 C Y $end
$var wire 1 S A $end
$upscope $end
$scope module _30_ $end
$var wire 1 D A $end
$var wire 1 C B $end
$var wire 1 B Y $end
$upscope $end
$scope module _31_ $end
$var wire 1 B B $end
$var wire 1 A Y $end
$var wire 1 K A $end
$upscope $end
$scope module _32_ $end
$var wire 1 @ Y $end
$var wire 1 K B $end
$var wire 1 Q A $end
$upscope $end
$scope module _33_ $end
$var wire 1 ( A $end
$var wire 1 @ B $end
$var wire 1 ? Y $end
$upscope $end
$scope module _34_ $end
$var wire 1 A A $end
$var wire 1 ? B $end
$var wire 1 Y Y $end
$upscope $end
$scope module _35_ $end
$var wire 1 T Y $end
$var wire 1 K B $end
$var wire 1 P A $end
$upscope $end
$scope module _36_ $end
$var wire 1 ' A $end
$var wire 1 S Y $end
$upscope $end
$scope module _37_ $end
$var wire 1 Z A $end
$var wire 1 R Y $end
$upscope $end
$scope module _38_ $end
$var wire 1 [ A $end
$var wire 1 Q Y $end
$upscope $end
$scope module _39_ $end
$var wire 1 ( A $end
$var wire 1 P Y $end
$upscope $end
$scope module _40_ $end
$var wire 1 & A $end
$var wire 1 O Y $end
$upscope $end
$scope module _41_ $end
$var wire 1 ' A $end
$var wire 1 % B $end
$var wire 1 N Y $end
$upscope $end
$scope module _42_ $end
$var wire 1 N A $end
$var wire 1 M Y $end
$upscope $end
$scope module _43_ $end
$var wire 1 ' A $end
$var wire 1 O B $end
$var wire 1 L Y $end
$upscope $end
$scope module _44_ $end
$var wire 1 M A $end
$var wire 1 L B $end
$var wire 1 K Y $end
$upscope $end
$scope module _45_ $end
$var wire 1 ' A $end
$var wire 1 \ B $end
$var wire 1 J Y $end
$upscope $end
$scope module _46_ $end
$var wire 1 S A $end
$var wire 1 ] B $end
$var wire 1 I Y $end
$upscope $end
$scope module _47_ $end
$var wire 1 - C $end
$var wire 1 T D $end
$var reg 1 # Q $end
$upscope $end
$scope module _48_ $end
$var wire 1 - C $end
$var wire 1 ^ D $end
$var reg 1 _ Q $end
$upscope $end
$scope module _49_ $end
$var wire 1 - C $end
$var wire 1 ` D $end
$var reg 1 a Q $end
$upscope $end
$upscope $end
$upscope $end
$scope module DFFSR $end
$var wire 1 b C $end
$var wire 1 c D $end
$var wire 1 d R $end
$var wire 1 e S $end
$var reg 1 f Q $end
$upscope $end
$enddefinitions $end
#0
$dumpvars
xf
ze
zd
zc
zb
xa
0`
x_
0^
0]
0\
x[
xZ
0Y
0X
0W
0V
b0 U
0T
1S
xR
xQ
1P
1O
1N
0M
0L
1K
1J
1I
0H
0G
xF
1E
1D
1C
0B
0A
x@
1?
bx >
b0 =
b0 <
0;
0:
b0 9
b0 8
b0 7
b0 6
b0 5
b0xx 4
b0xx 3
02
b0 1
bx 0
b0 /
b0 .
0-
bx ,
bx +
b0 *
b0 )
0(
0'
0&
0%
x$
x#
z"
z!
$end
#2000
0^
0`
0V
b0 U
0Y
0F
0@
1]
0S
1E
1?
1R
1Q
0O
b1 *
b1 .
b1 <
1'
0P
0Z
0[
0$
b0 3
b0 ,
b0 0
1;
1&
b1101 5
b1 9
1(
0#
0_
b0 4
b0 +
b0 >
0a
1-
#4000
0-
#6000
1`
b10 U
1Y
0?
0E
1T
1@
1F
1G
1B
0K
0D
1M
0N
1W
b10 1
12
b10 )
b10 /
b10 =
0;
1%
b11 8
b100 7
b1010 6
1-
#8000
0-
#10000
1^
0`
1V
b1 U
0Y
0G
1A
1H
0B
0I
0M
1D
1L
1N
0W
1S
0Q
b1 1
b0 )
b0 /
b0 =
0'
1[
1$
b10 3
b10 ,
b10 0
1;
1:
0%
b1111 8
b1110 7
b1000 6
b101 5
b10 9
1#
b10 4
b10 +
b10 >
1a
1-
#12000
0-
#14000
0J
1I
1M
0L
1Q
0R
0N
1\
0]
0S
0[
1Z
b1 )
b1 /
b1 =
b0 *
b0 .
b0 <
1'
0a
b1 4
b1 +
b1 >
1_
0;
1%
b1011 8
b1010 7
b1001 6
b100 5
b11 9
b1 3
b1 ,
b1 0
1-
#16000
0-
#18000
1`
b11 U
1Y
0A
1B
0D
1W
b11 1
1X
1]
b11 )
b11 /
b11 =
b11 *
b11 .
b11 <
b11 8
b1110 7
b1011 6
b111 5
b1 9
1;
0:
1-
#20000
0-
#22000
0`
0^
0Y
b0 U
0V
1A
1G
0B
0H
0M
1D
1L
1J
0Q
1N
1S
0W
0X
0]
1[
b0 1
0'
b1 )
b1 /
b1 =
b0 *
b0 .
b0 <
b11 4
b11 +
b11 >
1a
0%
b10 9
b1111 8
b1000 7
b101 6
b100 5
b11 3
b11 ,
b11 0
1-
#24000
0-
#26000
1`
b10 U
1Y
0A
1B
0C
0\
1X
1R
1Q
b10 1
b0 )
b0 /
b0 =
b10 *
b10 .
b10 <
0Z
0[
b0 3
b0 ,
b0 0
1:
1%
b1011 8
b1001 7
b0 6
b1010 5
b10 9
0_
b0 4
b0 +
b0 >
0a
1-
#28000
0-
#30000
0Q
1[
b10 4
b10 +
b10 >
1a
b10 3
b10 ,
b10 0
1-
