tarea5/probador.v
module probador(input [0:1] data_conductual,
		input [0:1] data_estructural,
		    output reg reset_L,
		    output reg [0:1] data_in0,
		    output reg [0:1] data_in1,
		    output reg selector,
		    output reg clk);
   initial begin
      $dumpfile("mux.vcd"); //Se depositan los datos en este archivo para leerlo en gtkwave
      $dumpvars;
      $display ("\t\t\tclk,\tdata_in0,\tdata_in1,\tdata_conductual,\treset_L ,\tselector");

      $monitor($time, "\t%b\t%b\t\t%b\t\t%b\t\t%b \t\t%b", clk, data_in0, data_in1, data_conductual, reset_L, selector); //Datos a mostar
      
      {selector, reset_L} <= 'b0; //Se inicializan estas entradas a 0
      {data_in0, data_in1} <= 2'b00; //Se inicializan entradas en 00



      @(posedge clk); //Como los pulsos no siguen una secuencia, se deben generar uno por uno en cada flanco
      reset_L <= 1;

      @(posedge clk);
      data_in0 <= 2'b11;
      data_in1 <= 2'b10;

      @(posedge clk);
      selector <= 1;
      data_in0 <= 2'b01;
      data_in1 <= 2'b00;

      @(posedge clk);
      data_in0 <= 2'b00;
      data_in1 <= 2'b10;

      @(posedge clk);
      selector <= 0;
      data_in0 <= 2'b11; 
      data_in1 <= 2'b11;

      @(posedge clk);
      selector <= 1;
      data_in0 <= 2'b00;
      data_in1 <= 2'b01;

      @(posedge clk);
      selector <= 0;
      data_in0 <= 2'b10;
      data_in1 <= 2'b00;

      @(posedge clk);

      @(posedge clk); //Para mostrar dos ciclo más
      
      
$finish;
      
   end // initial begin
  
   initial clk <= 0;
   always #3.3 clk <= ~clk;

endmodule // probador_mux

tarea5/sintetizado_cmos_delay.v
/* Generated by Yosys 0.9 (git sha1 1979e0b) */

(* top =  1  *)
(* src = "mux_delay.v:1" *)
module mux_delay(clk, reset_L, selector, data_in0, data_in1, data_out);
  (* src = "mux_delay.v:19" *)
  wire [1:0] _00_;
  wire _01_;
  wire _02_;
  wire _03_;
  wire _04_;
  wire _05_;
  wire _06_;
  wire _07_;
  wire _08_;
  (* src = "mux_delay.v:1" *)
  input clk;
  (* src = "mux_delay.v:4" *)
  input [1:0] data_in0;
  (* src = "mux_delay.v:5" *)
  input [1:0] data_in1;
  (* src = "mux_delay.v:6" *)
  output [1:0] data_out;
  (* src = "mux_delay.v:2" *)
  input reset_L;
  (* init = 2'h0 *)
  (* src = "mux_delay.v:8" *)
  (* unused_bits = "0 1" *)
  wire [1:0] salMux1;
  (* src = "mux_delay.v:3" *)
  input selector;
  NOT _09_ (
    .A(data_in1[0]),
    .Y(_08_)
  );
  NOT _10_ (
    .A(data_in1[1]),
    .Y(_01_)
  );
  NOR _11_ (
    .A(selector),
    .B(data_in0[1]),
    .Y(_02_)
  );
  NAND _12_ (
    .A(selector),
    .B(_01_),
    .Y(_03_)
  );
  NAND _13_ (
    .A(reset_L),
    .B(_03_),
    .Y(_04_)
  );
  NOR _14_ (
    .A(_02_),
    .B(_04_),
    .Y(_00_[1])
  );
  NOR _15_ (
    .A(data_in0[0]),
    .B(selector),
    .Y(_05_)
  );
  NAND _16_ (
    .A(_08_),
    .B(selector),
    .Y(_06_)
  );
  NAND _17_ (
    .A(reset_L),
    .B(_06_),
    .Y(_07_)
  );
  NOR _18_ (
    .A(_05_),
    .B(_07_),
    .Y(_00_[0])
  );
  (* src = "mux_delay.v:19" *)
  DFF _19_ (
    .C(clk),
    .D(_00_[0]),
    .Q(data_out[0])
  );
  (* src = "mux_delay.v:19" *)
  DFF _20_ (
    .C(clk),
    .D(_00_[1]),
    .Q(data_out[1])
  );
endmodule

tarea5/mux.v
module mux(input clk,
	   input 	    reset_L,
	   input 	    selector,
	   input [1:0] 	    data_in0,
	   input [1:0] 	    data_in1,
	   output reg [1:0] data_out);

   reg [1:0] salMux1 = 2'b00; //se genera un elemento para conexión capaz de almacenar datos
   
   
   always @(*) begin
      salMux1 = 1'b0; //se inicializa el valor de conexión a 0
      if (selector == 0)
	salMux1 = data_in0; //Dependiendo del valor del selector, se pasa a la salida del mux
      else
	salMux1 = data_in1;
   end

   always @(posedge clk) begin //Se hace otro elemento que lee únicamente en el flanco positivo de reloj, este elemento resetea o deja pasar el dato y lo guarda

      if (reset_L == 0)
	data_out <= 2'b00; //Si reset_L esta en 0 se resetea, caso contrario se pasa el dato del primer mux 
      else
	data_out <= salMux1;
   end
endmodule

tarea5/BancoPruebaConductual_delay.v
`timescale 1s / 1ms

`include "sintetizado_cmos_delay.v"
`include "probador.v"
`include "cmos_cells_retardos.v"
`include "mux.v"

module BancoPruebas;
   wire [1:0] data_in0, data_in1, data_conductual, data_estructural; //Se generan los cables de entrada (buses)
   wire [1:0] data_synth;
   wire       clk, salMux1, reset_L, selector; 
   
   mux p_conductual(/*AUTOINST*/
	      // Outputs
	      .data_out			(data_conductual[1:0]),
	      // Inputs
	      .clk			(clk),
	      .reset_L			(reset_L),
	      .selector			(selector),
	      .data_in0			(data_in0[1:0]),
	      .data_in1			(data_in1[1:0]));

   
   mux_delay p_delay(/*AUTOINST*/
	      // Outputs
	      .data_out			(data_estructural[1:0]),
	      // Inputs
	      .clk			(clk),
	      .reset_L			(reset_L),
	      .selector			(selector),
	      .data_in0			(data_in0[1:0]),
	      .data_in1			(data_in1[1:0]));
   
   
   probador probador(/*AUTOINST*/
			 // Outputs
			 .reset_L		(reset_L),
			 .data_in0		(data_in0[1:0]),
			 .data_in1		(data_in1[1:0]),
			 .selector		(selector),
			 .clk			(clk),
			 // Inputs
			 .data_estructural		(data_estructural[1:0]),
			.data_conductual		(data_conductual[1:0]));
   

endmodule

tarea5/cmos_cells_retardos.v

module BUF(A, Y);
input A;
output Y;
assign #(1.4:4.1:4.1) Y = A;
endmodule

module NOT(A, Y);
input A;
output Y;
assign #(1:3.5:6, 1:3.5:6) Y = ~A;
endmodule

module NAND(A, B, Y); //SN74LVC1G38
input A, B;
output Y;
assign #(0.9:1.6:2.4, 0.9:1.6:2.4) Y = ~(A & B);
endmodule

module NOR(A, B, Y);
input A, B;
output Y;
assign #(0.8:2.1:3.4, 0.8:2.1:3.4) Y = ~(A | B);
endmodule

module DFF(C, D, Q); //(1.1:2.4:3.8)
input C, D;
output reg Q;
always @(posedge C)
	#(1.1:2.4:3.8) Q <= D;
endmodule

module DFFSR(C, D, Q, S, R);
//assign #(1:3.5:6, 1:3.5:6)
input C, D, S, R;
output reg Q;
always @(posedge C, posedge S, posedge R)
	if (S)
		Q <= 1'b1;
	else if (R)
		Q <= 1'b0;
	else
		Q <= D;
endmodule

tarea5/mux.vcd
$date
	Tue Sep  8 22:23:46 2020
$end
$version
	Icarus Verilog
$end
$timescale
	1ms
$end
$scope module BUF $end
$var wire 1 ! A $end
$var wire 1 " Y $end
$upscope $end
$scope module BancoPruebas $end
$var wire 1 # selector $end
$var wire 1 $ reset_L $end
$var wire 2 % data_in1 [1:0] $end
$var wire 2 & data_in0 [1:0] $end
$var wire 2 ' data_estructural [1:0] $end
$var wire 2 ( data_conductual [1:0] $end
$var wire 1 ) clk $end
$scope module p_conductual $end
$var wire 1 # selector $end
$var wire 1 $ reset_L $end
$var wire 2 * data_in1 [1:0] $end
$var wire 2 + data_in0 [1:0] $end
$var wire 1 ) clk $end
$var reg 2 , data_out [1:0] $end
$var reg 2 - salMux1 [1:0] $end
$upscope $end
$scope module p_delay $end
$var wire 1 # selector $end
$var wire 1 $ reset_L $end
$var wire 2 . data_out [1:0] $end
$var wire 2 / data_in1 [1:0] $end
$var wire 2 0 data_in0 [1:0] $end
$var wire 1 ) clk $end
$var wire 1 1 _08_ $end
$var wire 1 2 _07_ $end
$var wire 1 3 _06_ $end
$var wire 1 4 _05_ $end
$var wire 1 5 _04_ $end
$var wire 1 6 _03_ $end
$var wire 1 7 _02_ $end
$var wire 1 8 _01_ $end
$var wire 2 9 _00_ [1:0] $end
$scope module _09_ $end
$var wire 1 : A $end
$var wire 1 1 Y $end
$upscope $end
$scope module _10_ $end
$var wire 1 ; A $end
$var wire 1 8 Y $end
$upscope $end
$scope module _11_ $end
$var wire 1 < B $end
$var wire 1 7 Y $end
$var wire 1 # A $end
$upscope $end
$scope module _12_ $end
$var wire 1 8 B $end
$var wire 1 6 Y $end
$var wire 1 # A $end
$upscope $end
$scope module _13_ $end
$var wire 1 6 B $end
$var wire 1 5 Y $end
$var wire 1 $ A $end
$upscope $end
$scope module _14_ $end
$var wire 1 7 A $end
$var wire 1 5 B $end
$var wire 1 = Y $end
$upscope $end
$scope module _15_ $end
$var wire 1 > A $end
$var wire 1 4 Y $end
$var wire 1 # B $end
$upscope $end
$scope module _16_ $end
$var wire 1 1 A $end
$var wire 1 3 Y $end
$var wire 1 # B $end
$upscope $end
$scope module _17_ $end
$var wire 1 3 B $end
$var wire 1 2 Y $end
$var wire 1 $ A $end
$upscope $end
$scope module _18_ $end
$var wire 1 4 A $end
$var wire 1 2 B $end
$var wire 1 ? Y $end
$upscope $end
$scope module _19_ $end
$var wire 1 @ D $end
$var wire 1 ) C $end
$var reg 1 A Q $end
$upscope $end
$scope module _20_ $end
$var wire 1 B D $end
$var wire 1 ) C $end
$var reg 1 C Q $end
$upscope $end
$upscope $end
$scope module probador $end
$var wire 2 D data_conductual [0:1] $end
$var wire 2 E data_estructural [0:1] $end
$var reg 1 ) clk $end
$var reg 2 F data_in0 [0:1] $end
$var reg 2 G data_in1 [0:1] $end
$var reg 1 $ reset_L $end
$var reg 1 # selector $end
$upscope $end
$upscope $end
$scope module DFFSR $end
$var wire 1 H C $end
$var wire 1 I D $end
$var wire 1 J R $end
$var wire 1 K S $end
$var reg 1 L Q $end
$upscope $end
$enddefinitions $end
#0
$dumpvars
xL
zK
zJ
zI
zH
b0 G
b0 F
bx E
bx D
xC
xB
xA
x@
x?
0>
x=
0<
0;
0:
bx 9
x8
x7
x6
x5
x4
x3
x2
x1
b0 0
b0 /
bx .
b0 -
bx ,
b0 +
b0 *
0)
bx (
bx '
b0 &
b0 %
0$
0#
x"
z!
$end
#1600
13
16
12
15
#2100
14
17
#3300
b0 (
b0 ,
b0 D
1$
1)
#3500
18
11
#3700
0@
0B
0?
b0 9
0=
#4100
z"
#4900
02
05
#5700
0A
b0 '
b0 .
b0 E
0C
#6600
0)
#9900
1;
1>
1<
b11 -
b10 %
b10 *
b10 /
b10 G
b11 &
b11 +
b11 0
b11 F
1)
#12000
04
07
#13200
0)
#13400
08
#14100
1@
1B
1?
b11 9
1=
#16500
0;
0<
b0 -
b11 (
b11 ,
b11 D
b0 %
b0 *
b0 /
b0 G
b1 &
b1 +
b1 0
b1 F
1#
1)
#18100
03
#18900
1A
b11 '
b11 .
b11 E
1C
#19700
12
#19800
0)
#20000
18
#21600
06
#21800
0@
b10 9
0?
#23100
1;
0>
b10 -
b10 %
b10 *
b10 /
b10 G
b0 &
b0 +
b0 0
b0 F
b0 (
b0 ,
b0 D
1)
#23200
15
#25300
0B
b0 9
0=
#25500
0C
b0 '
b0 .
b0 E
0A
#26400
0)
#26600
08
#28200
16
#29700
1:
1>
1<
b11 -
b10 (
b10 ,
b10 D
b11 %
b11 *
b11 /
b11 G
b11 &
b11 +
b11 0
b11 F
0#
1)
#29800
05
#31300
13
#31900
1B
b10 9
1=
#32100
b10 '
b10 .
b10 E
1C
#32900
02
#33000
0)
#33200
01
#35000
1@
b11 9
1?
#36300
0;
0>
0<
b1 -
b1 %
b1 *
b1 /
b1 G
b0 &
b0 +
b0 0
b0 F
1#
b11 (
b11 ,
b11 D
1)
#38700
b11 '
b11 .
b11 E
1A
#39600
0)
#39800
18
#41400
06
#42900
0:
1<
b10 -
b1 (
b1 ,
b1 D
b0 %
b0 *
b0 /
b0 G
b10 &
b10 +
b10 0
b10 F
0#
1)
#43000
15
#44500
16
#45000
14
#45100
0B
b1 9
0=
#45300
b1 '
b1 .
b1 E
0C
#46100
05
#46200
0)
#46400
11
#47100
0@
b0 9
0?
#48200
1B
b10 9
1=
#49500
b10 (
b10 ,
b10 D
1)
#51900
1C
b10 '
b10 .
b10 E
0A
